liqpay/__init__.py
liqpay/liqpay.py
liqpay/test.py
liqpay_python3-1.1.2.dist-info/METADATA
liqpay_python3-1.1.2.dist-info/WHEEL
liqpay_python3-1.1.2.dist-info/top_level.txt
liqpay_python3-1.1.2.dist-info/RECORD
